odoo/addons/mail_debrand/README.rst
odoo/addons/mail_debrand/__init__.py
odoo/addons/mail_debrand/__manifest__.py
odoo/addons/mail_debrand/i18n/da.po
odoo/addons/mail_debrand/i18n/de.po
odoo/addons/mail_debrand/i18n/es.po
odoo/addons/mail_debrand/i18n/es_MX.po
odoo/addons/mail_debrand/i18n/fr.po
odoo/addons/mail_debrand/i18n/hr.po
odoo/addons/mail_debrand/i18n/it.po
odoo/addons/mail_debrand/i18n/mail_debrand.pot
odoo/addons/mail_debrand/i18n/nl_NL.po
odoo/addons/mail_debrand/i18n/zh_CN.po
odoo/addons/mail_debrand/models/__init__.py
odoo/addons/mail_debrand/models/mail_template.py
odoo/addons/mail_debrand/static/description/icon.png
odoo/addons/mail_debrand/static/description/icon.svg
odoo/addons/mail_debrand/tests/__init__.py
odoo/addons/mail_debrand/tests/test_mail_debrand.py
odoo11_addon_mail_debrand-11.0.1.0.1.dist-info/METADATA
odoo11_addon_mail_debrand-11.0.1.0.1.dist-info/WHEEL
odoo11_addon_mail_debrand-11.0.1.0.1.dist-info/top_level.txt
odoo11_addon_mail_debrand-11.0.1.0.1.dist-info/RECORD
